{
  "name": "奥术派",
  "icon": "transcend:wand_master",
  "category": "transcend:lore",
  "pages": [
    {
      "type": "patchouli:spotlight",
      "item": "transcend:wand_master",
      "text": "$(o)「极端是病——平衡才是法。」$()$(br2)$(#FFAA00)奥术派$()被视为最古老、也最中庸的学派。他们不偏一元素，但通晓所有元素的「接缝」。"
    },
    {
      "type": "patchouli:text",
      "title": "信条",
      "text": "$(l)奥术派$()的三块平衡：$(br2)1. $(l)智慧大于力量$()$(br)2. $(l)节制大于堆砌$()$(br)3. $(l)所有学派皆有其理，但奥术派懂得为何$()$(br2)主元素：$(l)神圣$()、$(l)光$()、$(l)自然$()三元并修。"
    },
    {
      "type": "patchouli:text",
      "title": "历史",
      "text": "奥术派起源于第一座$(l)法术工作台$()的诞生地。当时的奥术学者编纂了《元素十八志》——直至今日仍是法师启蒙必读。$(br2)他们的法师以「全才」闻名，但每一项都不及专精学派的极限——这是他们的局限，也是他们的从容。"
    }
  ]
}
